chp_sim/__init__.py
chp_sim/chp_simulator.py
chp_sim/chp_simulator_test.py
chp_sim/version.py
chp_sim-0.1.1.dist-info/LICENSE
chp_sim-0.1.1.dist-info/METADATA
chp_sim-0.1.1.dist-info/WHEEL
chp_sim-0.1.1.dist-info/top_level.txt
chp_sim-0.1.1.dist-info/RECORD
