Metadata-Version: 2.1
Name: chp-sim
Version: 0.1.1
Summary: A reference implementation of Aaronson et al's CHP simulator for efficiently simulating quantum stabilizer circuits.
Home-page: https://github.com/Strilanc/python-chp-stabilizer-simulator
Author: Craig Gidney
Author-email: craig.gidney@gmail.com
License: Apache 2
Platform: UNKNOWN
Requires-Python: >=3.6.0
Requires-Dist: numpy
